fastapi_sqlmodel/__init__.py
fastapi_sqlmodel/exceptions.py
fastapi_sqlmodel/middleware.py
FastAPI_SQLModel-0.0.1.dist-info/LICENSE
FastAPI_SQLModel-0.0.1.dist-info/METADATA
FastAPI_SQLModel-0.0.1.dist-info/WHEEL
FastAPI_SQLModel-0.0.1.dist-info/top_level.txt
FastAPI_SQLModel-0.0.1.dist-info/RECORD
