Metadata-Version: 2.1
Name: FastAPI-SQLModel
Version: 0.0.1
Summary: Adds simple SQLModel support to FastAPI
Home-page: https://github.com/hitman-gdg/fastapi-sqlmodel
Author: Shawn Martin
Author-email: hitman.gdg@gmail.com
License: MIT
Project-URL: Code, https://github.com/hitman-gdg/fastapi-sqlmodel
Project-URL: Issue tracker, https://github.com/hitman-gdg/fastapi-sqlmodel/issues
Platform: UNKNOWN
Classifier: Development Status :: 4 - Beta
Classifier: Environment :: Web Environment
Classifier: Framework :: AsyncIO
Classifier: Intended Audience :: Developers
Classifier: License :: OSI Approved :: MIT License
Classifier: Operating System :: OS Independent
Classifier: Programming Language :: Python :: 3.6
Classifier: Programming Language :: Python :: 3.7
Classifier: Programming Language :: Python :: 3.8
Classifier: Programming Language :: Python :: 3.9
Classifier: Programming Language :: Python :: 3.10
Classifier: Programming Language :: Python :: 3 :: Only
Classifier: Programming Language :: Python :: Implementation :: CPython
Classifier: Topic :: Internet :: WWW/HTTP :: HTTP Servers
Classifier: Topic :: Internet :: WWW/HTTP :: Dynamic Content
Classifier: Topic :: Software Development :: Libraries :: Python Modules
Requires-Python: >=3.9
License-File: LICENSE
